Workbook

Sheet dashboard
B2: ⚖ VALUTAZIONE PREVENTIVA CRISI D'IMPRESA · CRUSCOTTO
B3: D.Lgs. 14/2019 — Codice della Crisi d'Impresa e dell'Insolvenza — versione Aziende
B5: FASCICOLO
B6: Azienda | E6: Forma giuridica | G6: Procedura ipotizzata
B7: =IF(anagrafica_azienda!C6="","- da compilare -",anagrafica_azienda!C6) -> - da compilare - | E7: =IF(anagrafica_azienda!C7="","- da compilare -",anagrafica_azienda!C7) -> - da compilare - | G7: =IF(anagrafica_azienda!C29="","- da compilare -",anagrafica_azienda!C29) -> - da compilare -
B9: Tribunale competente | E9: Advisor | G9: Data situazione di riferimento
B10: =IF(anagrafica_azienda!C25="","- da compilare -",anagrafica_azienda!C25) -> - da compilare - | E10: =IF(anagrafica_azienda!C21="","- da compilare -",anagrafica_azienda!C21) -> - da compilare - | G10: =IF(anagrafica_azienda!C30="","- da compilare -",anagrafica_azienda!C30) -> - da compilare -
B12: RIEPILOGO PATRIMONIALE E FINANZIARIO (ultimo esercizio)
B13: TOTALE ATTIVO | D13: TOTALE PASSIVO | F13: PATRIMONIO NETTO | H13: EBITDA ULTIMO ESERCIZIO
B14: =bilancio_sp!E20 -> 0 | D14: =bilancio_sp!E41 -> 0 | F14: =bilancio_sp!E27 -> 0 | H14: =bilancio_ce!E18 -> 0
B16: CURRENT RATIO | D16: LEVERAGE (PASSIVO/PN) | F16: DSCR PROSPETTICO A 6 MESI | H16: SEMAFORO ALLERTA CCII
B17: =indici_bilancio!E8 -> n.d. | D17: =indici_bilancio!E12 -> n.d. | F17: =flussi_cassa!D18 -> n.d. | H17: =allerta_ccii!C27 -> ROSSO - piu indicatori in allerta, valutare con advisor
B19: PASSIVO PER CLASSE | G19: AVANZAMENTO FASCICOLO
B20: Prededucibile | D20: =passivo_creditori!C8 -> 0 | G20: Documenti ricevuti / totale | I20: =COUNTIF(documenti!C6:C46,"Ricevuto")&" / "&COUNTA(documenti!C6:C46) -> 0 / 29
B21: Privilegio speciale (ipoteca / pegno) | D21: =passivo_creditori!C9 -> 0 | G21: % documenti ricevuti | I21: =IFERROR(COUNTIF(documenti!C6:C46,"Ricevuto")/COUNTA(documenti!C6:C46),"n.d.") -> 0
B22: Privilegio generale - lavoratori (art. 2751-bis c.c.) | D22: =passivo_creditori!C10 -> 0 | G22: Criticita' rilevate (indicatori allerta) | I22: =allerta_ccii!C26 -> 3
B23: Privilegio generale - tributi e contributi | D23: =passivo_creditori!C11 -> 0 | G23: Test PN (capitale minimo / negativo) | I23: =allerta_ccii!C9 -> PN SOTTO IL MINIMO LEGALE
B24: Chirografario | D24: =passivo_creditori!C12 -> 0
B26: Cruscotto ad uso interno per la valutazione preventiva: tutti i valori sono collegati (celle verdi) ai fogli di dettaglio. Compilare anagrafica_azienda, bilancio_sp, bilancio_ce, flussi_cassa e passivo_creditori; gli altri fogli si aggiornano automaticamente. Nessuna macro, nessuna protezione: il file e' interamente modificabile.

Sheet anagrafica_azienda
B2: ANAGRAFICA AZIENDA
B3: Dati identificativi, organi e inquadramento della crisi
B5: DATI IDENTIFICATIVI
B6: Ragione sociale
B7: Forma giuridica
B8: Partita IVA
B9: Codice fiscale
B10: Sede legale
B11: Numero REA / CCIAA
B12: Settore ATECO
B13: Data di costituzione
B14: Capitale sociale (€) | C14: 0
B15: N. dipendenti attuali | C15: 0
B16: Stato dell'impresa
B18: ORGANI E PROFESSIONISTI
B19: Legale rappresentante
B20: Organo di controllo (sindaco / revisore)
B21: Advisor / consulente incaricato
B22: C.F. Advisor
B23: Attestatore (se nominato)
B24: Curatore / Commissario / Liquidatore (se nominato)
B25: Tribunale competente
B26: N. R.G. (se procedura aperta)
B28: INQUADRAMENTO DELLA CRISI
B29: Procedura ipotizzata / in corso
... B38: Legenda: celle su sfondo giallo pallido e testo blu = dati da inserire manualmente. I fogli successivi richiamano automaticamente i dati inseriti qui (celle in verde = collegamento ad altro foglio).

Sheet bilancio_sp
B2: BILANCIO · STATO PATRIMONIALE RICLASSIFICATO
B3: Valori in euro · inserire i dati di bilancio nelle colonne gialle
B4: ="Riclassificazione a criterio finanziario — "&anagrafica_azienda!C6 -> Riclassificazione a criterio finanziario —
B5: Voce | C5: Anno -2 | D5: Anno -1 | E5: Anno corrente / previsionale
B6: ATTIVO
B7: Immobilizzazioni immateriali | C7: 0 | D7: 0 | E7: 0
B8: Immobilizzazioni materiali | C8: 0 | D8: 0 | E8: 0
B9: Immobilizzazioni finanziarie | C9: 0 | D9: 0 | E9: 0
B10: TOTALE IMMOBILIZZAZIONI (B) | C10: =C7+C8+C9 -> 0 | D10: =D7+D8+D9 -> 0 | E10: =E7+E8+E9 -> 0
B12: Rimanenze (magazzino) | C12: 0 | D12: 0 | E12: 0
B13: Crediti verso clienti | C13: 0 | D13: 0 | E13: 0
B14: Altri crediti a breve | C14: 0 | D14: 0 | E14: 0
B15: Disponibilita' liquide (cassa e banche) | C15: 0 | D15: 0 | E15: 0
B16: TOTALE ATTIVO CIRCOLANTE (C) | C16: =SUM(C12:C15) -> 0 | D16: =SUM(D12:D15) -> 0 | E16: =SUM(E12:E15) -> 0
B18: Ratei e risconti attivi (D) | C18: 0 | D18: 0 | E18: 0
B20: TOTALE ATTIVO | C20: =C10+C16+C18 -> 0 | D20: =D10+D16+D18 -> 0 | E20: =E10+E16+E18 -> 0
B22: PASSIVO
B23: Capitale sociale | C23: 0 | D23: 0 | E23: 0
B24: Riserve | C24: 0 | D24: 0 | E24: 0
B25: Utile/(perdita) esercizi precedenti | C25: 0 | D25: 0 | E25: 0
B26: Utile/(perdita) dell'esercizio | C26: =bilancio_ce!C30 -> 0 | D26: =bilancio_ce!D30 -> 0 | E26: =bilancio_ce!E30 -> 0
B27: TOTALE PATRIMONIO NETTO (A) | C27: =C23+C24+C25+C26 -> 0 | D27: =D23+D24+D25+D26 -> 0 | E27: =E23+E24+E25+E26 -> 0
B29: Fondi per rischi e oneri | C29: 0 | D29: 0 | E29: 0
B30: TFR - Trattamento di fine rapporto | C30: 0 | D30: 0 | E30: 0
B31: Debiti verso banche (oltre 12 mesi) | C31: 0 | D31: 0 | E31: 0
B32: Debiti verso banche (entro 12 mesi) | C32: 0 | D32: 0 | E32: 0
B33: Debiti verso fornitori | C33: 0 | D33: 0 | E33: 0
B34: Debiti tributari | C34: 0 | D34: 0 | E34: 0
B35: Debiti verso istituti previdenziali | C35: 0 | D35: 0 | E35: 0
B36: Altri debiti | C36: 0 | D36: 0 | E36: 0
B37: TOTALE DEBITI E FONDI (D) | C37: =C29+C30+C31+C32+C33+C34+C35+C36 -> 0 | D37: =D29+D30+D31+D32+D33+D34+D35+D36 -> 0 | E37: =E29+E30+E31+E32+E33+E34+E35+E36 -> 0
B39: Ratei e risconti passivi (E) | C39: 0 | D39: 0 | E39: 0
B41: TOTALE PASSIVO | C41: =C27+C37+C39 -> 0 | D41: =D27+D37+D39 -> 0 | E41: =E27+E37+E39 -> 0
B43: Quadratura (Attivo - Passivo, deve essere 0) | C43: =C20-C41 -> 0 | D43: =D20-D41 -> 0 | E43: =E20-E41 -> 0
B45: INDICATORI DI SINTESI PATRIMONIALE
B46: Capitale Circolante Netto (CCN) = Att.circolante - Debiti a breve + ratei | C46: =C16-(C32+C33+C34+C35+C36)+C18-C39 -> 0 | D46: =D16-(D32+D33+D34+D35+D36)+D18-D39 -> 0 | E46: =E16-(E32+E33+E34+E35+E36)+E18-E39 -> 0
B47: Patrimonio Netto negativo? (campanello d'allarme art. 2482-bis/ter c.c.) | C47: =IF(C27<0,"SI - PN NEGATIVO","no") -> no | D47: =IF(D27<0,"SI - PN NEGATIVO","no") -> no | E47: =IF(E27<0,"SI - PN NEGATIVO","no") -> no
B49: Fonte: inserire i valori dagli ultimi 3 bilanci depositati (o situazione contabile infrannuale per l'anno corrente). La colonna 'Anno corrente / previsionale' puo' ospitare anche una situazione infrannuale aggiornata alla data di analisi. 'Utile/(perdita) dell'esercizio' e' collegato automaticamente al foglio bilancio_ce.

Sheet bilancio_ce
B2: BILANCIO · CONTO ECONOMICO RICLASSIFICATO A VALORE AGGIUNTO
B3: Valori in euro · inserire i dati di bilancio nelle colonne gialle
B5: Voce | C5: Anno -2 | D5: Anno -1 | E5: Anno corrente / previsionale
B6: Ricavi delle vendite e delle prestazioni | C6: 0 | D6: 0 | E6: 0
B7: Variazione delle rimanenze di prodotti | C7: 0 | D7: 0 | E7: 0
B8: Altri ricavi e proventi | C8: 0 | D8: 0 | E8: 0
B9: VALORE DELLA PRODUZIONE | C9: =C6+C7+C8 -> 0 | D9: =D6+D7+D8 -> 0 | E9: =E6+E7+E8 -> 0
B11: Costi per materie prime, sussidiarie e merci | C11: 0 | D11: 0 | E11: 0
B12: Costi per servizi | C12: 0 | D12: 0 | E12: 0
B13: Costi per godimento beni di terzi | C13: 0 | D13: 0 | E13: 0
B14: Oneri diversi di gestione | C14: 0 | D14: 0 | E14: 0
B15: VALORE AGGIUNTO | C15: =C9-C11-C12-C13-C14 -> 0 | D15: =D9-D11-D12-D13-D14 -> 0 | E15: =E9-E11-E12-E13-E14 -> 0
B17: Costo del personale (incl. oneri e TFR) | C17: 0 | D17: 0 | E17: 0
B18: EBITDA (MARGINE OPERATIVO LORDO) | C18: =C15-C17 -> 0 | D18: =D15-D17 -> 0 | E18: =E15-E17 -> 0
B20: Ammortamenti e svalutazioni | C20: 0 | D20: 0 | E20: 0
B21: Accantonamenti per rischi e oneri | C21: 0 | D21: 0 | E21: 0
B22: EBIT (RISULTATO OPERATIVO) | C22: =C18-C20-C21 -> 0 | D22: =D18-D20-D21 -> 0 | E22: =E18-E20-E21 -> 0
B24: Proventi finanziari | C24: 0 | D24: 0 | E24: 0
B25: Oneri finanziari | C25: 0 | D25: 0 | E25: 0
B26: Componenti straordinarie / non ricorrenti (nette) | C26: 0 | D26: 0 | E26: 0
B27: EBT (RISULTATO ANTE IMPOSTE) | C27: =C22+C24-C25+C26 -> 0 | D27: =D22+D24-D25+D26 -> 0 | E27: =E22+E24-E25+E26 -> 0
B29: Imposte sul reddito (correnti e differite) | C29: 0 | D29: 0 | E29: 0
B30: UTILE / (PERDITA) NETTO D'ESERCIZIO | C30: =C27-C29 -> 0 | D30: =D27-D29 -> 0 | E30: =E27-E29 -> 0
B32: MARGINI IN % DEI RICAVI
B33: EBITDA margin (EBITDA / Ricavi) | C33: =IFERROR(C18/C6,"n.d.") -> n.d. | D33: =IFERROR(D18/D6,"n.d.") -> n.d. | E33: =IFERROR(E18/E6,"n.d.") -> n.d.
B34: EBIT margin (EBIT / Ricavi) | C34: =IFERROR(C22/C6,"n.d.") -> n.d. | D34: =IFERROR(D22/D6,"n.d.") -> n.d. | E34: =IFERROR(E22/E6,"n.d.") -> n.d.
B35: Incidenza costo del personale su Valore Aggiunto | C35: =IFERROR(C17/C15,"n.d.") -> n.d. | D35: =IFERROR(D17/D15,"n.d.") -> n.d. | E35: =IFERROR(E17/E15,"n.d.") -> n.d.
B37: Fonte: riclassificazione a valore aggiunto dai bilanci depositati (voci A/B del Conto Economico civilistico art. 2425 c.c.). Per l'anno corrente usare l'ultima situazione contabile disponibile o il budget previsionale, specificando la fonte in una nota separata.

Sheet indici_bilancio
B2: INDICI DI BILANCIO
B3: Indici di liquidita', solidita', redditivita' ed efficienza — calcolati automaticamente da bilancio_sp e bilancio_ce
B5: Indice | C5: Anno -2 | D5: Anno -1 | E5: Anno corrente / previsionale
B6: LIQUIDITA'
B7: Capitale Circolante Netto (CCN) | C7: =bilancio_sp!C46 -> 0 | D7: =bilancio_sp!D46 -> 0 | E7: =bilancio_sp!E46 -> 0
B8: Current ratio (Attivo circ. / Debiti a breve) | C8: =IFERROR(bilancio_sp!C16/(bilancio_sp!C32+bilancio_sp!C33+bilancio_sp!C34+bilancio_sp!C35+bilancio_sp!C36),"n.d.") -> n.d. | D8: =IFERROR(bilancio_sp!D16/(bilancio_sp!D32+bilancio_sp!D33+bilancio_sp!D34+bilancio_sp!D35+bilancio_sp!D36),"n.d.") -> n.d. | E8: =IFERROR(bilancio_sp!E16/(bilancio_sp!E32+bilancio_sp!E33+bilancio_sp!E34+bilancio_sp!E35+bilancio_sp!E36),"n.d.") -> n.d.
B9: Quick ratio (Att.circ. - Rimanenze) / Debiti a breve | C9: =IFERROR((bilancio_sp!C16-bilancio_sp!C12)/(bilancio_sp!C32+bilancio_sp!C33+bilancio_sp!C34+bilancio_sp!C35+bilancio_sp!C36),"n.d.") -> n.d. | D9: =IFERROR((bilancio_sp!D16-bilancio_sp!D12)/(bilancio_sp!D32+bilancio_sp!D33+bilancio_sp!D34+bilancio_sp!D35+bilancio_sp!D36),"n.d.") -> n.d. | E9: =IFERROR((bilancio_sp!E16-bilancio_sp!E12)/(bilancio_sp!E32+bilancio_sp!E33+bilancio_sp!E34+bilancio_sp!E35+bilancio_sp!E36),"n.d.") -> n.d.
B11: SOLIDITA'
B12: Indice di indebitamento (Leverage = Tot.Passivo / PN) | C12: =IFERROR(bilancio_sp!C41/bilancio_sp!C27,"n.d.") -> n.d. | D12: =IFERROR(bilancio_sp!D41/bilancio_sp!D27,"n.d.") -> n.d. | E12: =IFERROR(bilancio_sp!E41/bilancio_sp!E27,"n.d.") -> n.d.
B13: Indice di autonomia finanziaria (PN / Tot.Attivo) | C13: =IFERROR(bilancio_sp!C27/bilancio_sp!C20,"n.d.") -> n.d. | D13: =IFERROR(bilancio_sp!D27/bilancio_sp!D20,"n.d.") -> n.d. | E13: =IFERROR(bilancio_sp!E27/bilancio_sp!E20,"n.d.") -> n.d.
B14: Indice di copertura immobilizzazioni (PN / Immob.) | C14: =IFERROR(bilancio_sp!C27/bilancio_sp!C10,"n.d.") -> n.d. | D14: =IFERROR(bilancio_sp!D27/bilancio_sp!D10,"n.d.") -> n.d. | E14: =IFERROR(bilancio_sp!E27/bilancio_sp!E10,"n.d.") -> n.d.
B15: Debiti finanziari / EBITDA | C15: =IFERROR((bilancio_sp!C31+bilancio_sp!C32)/bilancio_ce!C18,"n.d.") -> n.d. | D15: =IFERROR((bilancio_sp!D31+bilancio_sp!D32)/bilancio_ce!D18,"n.d.") -> n.d. | E15: =IFERROR((bilancio_sp!E31+bilancio_sp!E32)/bilancio_ce!E18,"n.d.") -> n.d.
B17: REDDITIVITA'
B18: ROE (Utile netto / Patrimonio Netto) | C18: =IFERROR(bilancio_ce!C30/bilancio_sp!C27,"n.d.") -> n.d. | D18: =IFERROR(bilancio_ce!D30/bilancio_sp!D27,"n.d.") -> n.d. | E18: =IFERROR(bilancio_ce!E30/bilancio_sp!E27,"n.d.") -> n.d.
B19: ROI approssimato (EBIT / Totale Attivo) | C19: =IFERROR(bilancio_ce!C22/bilancio_sp!C20,"n.d.") -> n.d. | D19: =IFERROR(bilancio_ce!D22/bilancio_sp!D20,"n.d.") -> n.d. | E19: =IFERROR(bilancio_ce!E22/bilancio_sp!E20,"n.d.") -> n.d.
B20: ROS (EBIT / Ricavi) | C20: =IFERROR(bilancio_ce!C22/bilancio_ce!C6,"n.d.") -> n.d. | D20: =IFERROR(bilancio_ce!D22/bilancio_ce!D6,"n.d.") -> n.d. | E20: =IFERROR(bilancio_ce!E22/bilancio_ce!E6,"n.d.") -> n.d.
B21: ROA (Utile netto / Totale Attivo) | C21: =IFERROR(bilancio_ce!C30/bilancio_sp!C20,"n.d.") -> n.d. | D21: =IFERROR(bilancio_ce!D30/bilancio_sp!D20,"n.d.") -> n.d. | E21: =IFERROR(bilancio_ce!E30/bilancio_sp!E20,"n.d.") -> n.d.
B23: EFFICIENZA E ROTAZIONE (in giorni)
B24: DSO - giorni medi incasso crediti clienti | C24: =IFERROR(bilancio_sp!C13/bilancio_ce!C6*365,"n.d.") -> n.d. | D24: =IFERROR(bilancio_sp!D13/bilancio_ce!D6*365,"n.d.") -> n.d. | E24: =IFERROR(bilancio_sp!E13/bilancio_ce!E6*365,"n.d.") -> n.d.
B25: DPO - giorni medi pagamento fornitori | C25: =IFERROR(bilancio_sp!C33/(bilancio_ce!C11+bilancio_ce!C12)*365,"n.d.") -> n.d. | D25: =IFERROR(bilancio_sp!D33/(bilancio_ce!D11+bilancio_ce!D12)*365,"n.d.") -> n.d. | E25: =IFERROR(bilancio_sp!E33/(bilancio_ce!E11+bilancio_ce!E12)*365,"n.d.") -> n.d.
B26: DIO - giorni medi di giacenza magazzino | C26: =IFERROR(bilancio_sp!C12/(bilancio_ce!C11+bilancio_ce!C12)*365,"n.d.") -> n.d. | D26: =IFERROR(bilancio_sp!D12/(bilancio_ce!D11+bilancio_ce!D12)*365,"n.d.") -> n.d. | E26: =IFERROR(bilancio_sp!E12/(bilancio_ce!E11+bilancio_ce!E12)*365,"n.d.") -> n.d.
B27: Ciclo di cassa (DSO + DIO - DPO) | C27: =IFERROR(C24+C26-C25,"n.d.") -> n.d. | D27: =IFERROR(D24+D26-D25,"n.d.") -> n.d. | E27: =IFERROR(E24+E26-E25,"n.d.") -> n.d.
B29: ROI qui inteso in forma approssimata (EBIT/Totale Attivo); per un ROI in senso stretto occorrerebbe isolare il solo capitale investito operativo, al netto delle attivita' extra-caratteristiche — adattare se rilevante per il caso concreto.

Sheet flussi_cassa
B2: FLUSSI DI CASSA PROSPETTICI A 12 MESI
B3: Test di continuita' aziendale e DSCR — inserire i dati nelle colonne gialle
B4: Orizzonte: 12 mesi dalla data di riferimento indicata in anagrafica_azienda!C30
B5: Voce | D5: Mese 1 | E5: Mese 2 | F5: Mese 3 | G5: Mese 4 | H5: Mese 5 | I5: Mese 6 | J5: Mese 7 | K5: Mese 8 | L5: Mese 9 | M5: Mese 10 | N5: Mese 11 | O5: Mese 12
B6: Saldo iniziale di cassa | D6: 0 | E6: =D12 -> 0 | F6: =E12 -> 0 | G6: =F12 -> 0 | H6: =G12 -> 0 | I6: =H12 -> 0 | J6: =I12 -> 0 | K6: =J12 -> 0 | L6: =K12 -> 0 | ... O6: =N12 -> 0
B7: Incassi operativi (clienti + altri incassi) | D7: 0 | E7: 0 | F7: 0 | G7: 0 | H7: 0 | I7: 0 | J7: 0 | K7: 0 | L7: 0 | M7: 0 | N7: 0 | O7: 0
B8: Uscite operative (fornitori, personale, tributi, altri — escluse rate) | D8: 0 | E8: 0 | F8: 0 | G8: 0 | H8: 0 | I8: 0 | J8: 0 | K8: 0 | L8: 0 | M8: 0 | N8: 0 | O8: 0
B9: FLUSSO OPERATIVO NETTO DEL MESE | D9: =D7-D8 -> 0 | E9: =E7-E8 -> 0 | F9: =F7-F8 -> 0 | G9: =G7-G8 -> 0 | H9: =H7-H8 -> 0 | I9: =I7-I8 -> 0 | J9: =J7-J8 -> 0 | K9: =K7-K8 -> 0 | ... O9: =O7-O8 -> 0
B10: Rate di debito (capitale + interessi) in scadenza nel mese | D10: 0 | E10: 0 | F10: 0 | G10: 0 | H10: 0 | I10: 0 | J10: 0 | K10: 0 | L10: 0 | M10: 0 | N10: 0 | O10: 0
B11: FLUSSO DI CASSA NETTO DEL MESE (dopo servizio del debito) | D11: =D9-D10 -> 0 | E11: =E9-E10 -> 0 | F11: =F9-F10 -> 0 | G11: =G9-G10 -> 0 | H11: =H9-H10 -> 0 | I11: =I9-I10 -> 0 | J11: =J9-J10 -> 0 | K11: =K9-K10 -> 0 | ... O11: =O9-O10 -> 0
B12: SALDO FINALE DI CASSA | D12: =D6+D11 -> 0 | E12: =E6+E11 -> 0 | F12: =F6+F11 -> 0 | G12: =G6+G11 -> 0 | H12: =H6+H11 -> 0 | I12: =I6+I11 -> 0 | J12: =J6+J11 -> 0 | K12: =K6+K11 -> 0 | ... O12: =O6+O11 -> 0
B13: DSCR mensile (Flusso operativo / Rata del mese) | D13: =IFERROR(D9/D10,"n.d.") -> n.d. | E13: =IFERROR(E9/E10,"n.d.") -> n.d. | F13: =IFERROR(F9/F10,"n.d.") -> n.d. | G13: =IFERROR(G9/G10,"n.d.") -> n.d. | H13: =IFERROR(H9/H10,"n.d.") -> n.d. | I13: =IFERROR(I9/I10,"n.d.") -> n.d. | J13: =IFERROR(J9/J10,"n.d.") -> n.d. | K13: =IFERROR(K9/K10,"n.d.") -> n.d. | ... O13: =IFERROR(O9/O10,"n.d.") -> n.d.
B15: SINTESI SEMESTRALE PER IL TEST DSCR (art. 3 CCII)
B16: Somma flusso operativo netto - primi 6 mesi | D16: =SUM(D9:I9) -> 0
B17: Somma rate di debito in scadenza - primi 6 mesi | D17: =SUM(D10:I10) -> 0
B18: DSCR a 6 mesi (prospettico) | D18: =IFERROR(D16/D17,"n.d.") -> n.d.
B19: Saldo di cassa minimo previsto nei 12 mesi | D19: =MIN(D12:O12) -> 0
B20: Mese con saldo di cassa piu' basso | D20: =INDEX(D5:O5,MATCH(D19,D12:O12,0)) -> Mese 1
B22: Il DSCR (Debt Service Coverage Ratio) confronta il flusso di cassa operativo disponibile con il servizio del debito (rate capitale+interessi) nell'orizzonte di riferimento; e' l'indicatore-chiave richiamato dall'art. 3 CCII e dal Principio di attestazione. Soglia indicativa generalmente utilizzata: DSCR >= 1 nei 6 mesi successivi.

Sheet allerta_ccii
B2: INDICATORI DI ALLERTA E ADEGUATEZZA DEGLI ASSETTI (art. 3 CCII)
B3: Test del patrimonio netto, DSCR prospettico e indicatori CNDCEC
B6: TEST DEL PATRIMONIO NETTO
B7: Patrimonio Netto (ultimo esercizio) | C7: =bilancio_sp!E27 -> 0
B8: Capitale sociale minimo di legge per la forma giuridica | C8: 10000 | D8: €10.000 S.r.l. (€1 se s.r.l.s./PMI semplificata) · €50.000 S.p.A./S.a.p.a. — verificare il caso concreto
B9: Esito | C9: =IF(C7<0,"PN NEGATIVO",IF(C7<C8,"PN SOTTO IL MINIMO LEGALE","OK")) -> PN SOTTO IL MINIMO LEGALE
B11: DSCR PROSPETTICO A 6 MESI
B12: DSCR a 6 mesi (da flussi_cassa) | C12: =flussi_cassa!D18 -> n.d.
B13: Soglia minima indicativa | C13: 1
B14: Esito | C14: =IF(ISNUMBER(C12),IF(C12>=C13,"OK","DSCR INSUFFICIENTE"),"n.d.") -> n.d.
B16: INDICATORI SIGNIFICATIVI (rif. indicatori CNDCEC ex art. 3 CCII)
B17: Indicatore | C17: Valore | D17: Soglia di riferimento (indicativa, da aggiornare per settore) | E17: Esito
B18: Sostenibilita' oneri finanziari (Oneri fin. / Ricavi) | C18: =IFERROR(bilancio_ce!E25/bilancio_ce!E6,"n.d.") -> n.d. | D18: 0.02 | E18: =IF(C18<=D18,"OK","SUPERATA") -> SUPERATA
B19: Adeguatezza patrimoniale (PN / Debiti totali) | C19: =IFERROR(bilancio_sp!E27/(bilancio_sp!E37),"n.d.") -> n.d. | D19: 0 | E19: =IF(C19>=D19,"OK","NON RAGGIUNTA") -> OK
B20: Ritorno liquido dell'attivo (Cash flow / Tot. Attivo) | C20: =IFERROR((bilancio_ce!E18)/bilancio_sp!E20,"n.d.") -> n.d. | D20: 0.02 | E20: =IF(C20>=D20,"OK","NON RAGGIUNTA") -> OK
B21: Liquidita' (Attivo circolante / Passivo a breve) | C21: =IFERROR(bilancio_sp!E16/(bilancio_sp!E32+bilancio_sp!E33+bilancio_sp!E34+bilancio_sp!E35+bilancio_sp!E36),"n.d.") -> n.d. | D21: 1 | E21: =IF(C21>=D21,"OK","NON RAGGIUNTA") -> OK
B22: Indebitamento previdenziale e tributario scaduto / Attivo | C22: 0 | D22: 0.05 | E22: =IF(C22<=D22,"OK","SUPERATA") -> OK
B23: Le soglie 2024-2025 pubblicate dal CNDCEC sono differenziate per settore ATECO e vanno reperite di anno in anno; i valori sopra sono soglie generiche di lavoro (colonna D, modificabile) da sostituire con quelle ufficiali del settore specifico prima di ogni valutazione formale. 'Indebitamento previdenziale e tributario scaduto' va inserito manualmente (colonna C) perche' non desumibile dal solo bilancio riclassificato.
B25: SEMAFORO COMPLESSIVO
B26: N. indicatori con esito diverso da OK (su 7: PN, DSCR, 5 indicatori CNDCEC) | C26: =COUNTIF(C9,"<>OK")+COUNTIF(C14,"<>OK")+COUNTIF(E18:E22,"<>OK") -> 3
B27: Esito complessivo | C27: =IF(C26=0,"VERDE - nessuna criticita rilevata",IF(C26<=2,"GIALLO - approfondire con adeguati assetti","ROSSO - piu indicatori in allerta, valutare con advisor")) -> ROSSO - piu indicatori in allerta, valutare con advisor

Sheet passivo_creditori
B2: PASSIVO · ELENCO CREDITORI PER CLASSE E GRADO DI PRELAZIONE
B3: Compilare la tabella creditori — i totali per classe si aggiornano automaticamente
B6: RIEPILOGO PASSIVO PER CLASSE
B7: Classe | C7: Totale | D7: % sul totale passivo
B8: Prededucibile | C8: =SUMIF($B$17:$B$41,$B8,$F$17:$F$41) -> 0 | D8: =IFERROR(C8/C$13,"n.d.") -> n.d.
B9: Privilegio speciale (ipoteca / pegno) | C9: =SUMIF($B$17:$B$41,$B9,$F$17:$F$41) -> 0 | D9: =IFERROR(C9/C$13,"n.d.") -> n.d.
B10: Privilegio generale - lavoratori (art. 2751-bis c.c.) | C10: =SUMIF($B$17:$B$41,$B10,$F$17:$F$41) -> 0 | D10: =IFERROR(C10/C$13,"n.d.") -> n.d.
B11: Privilegio generale - tributi e contributi | C11: =SUMIF($B$17:$B$41,$B11,$F$17:$F$41) -> 0 | D11: =IFERROR(C11/C$13,"n.d.") -> n.d.
B12: Chirografario | C12: =SUMIF($B$17:$B$41,$B12,$F$17:$F$41) -> 0 | D12: =IFERROR(C12/C$13,"n.d.") -> n.d.
B13: TOTALE PASSIVO | C13: =SUM(C8:C12) -> 0 | D13: =IFERROR(C13/C13,"n.d.") -> n.d.
B15: ELENCO ANALITICO DEI CREDITORI
B16: Classe | C16: Creditore | D16: Natura del credito | E16: Bene / garanzia | F16: Importo €
F17: 0
F18: 0
F19: 0
F20: 0
F21: 0
F22: 0
F23: 0
F24: 0
F25: 0
F26: 0
F27: 0
F28: 0
... F41: 0
B42: Totale | F42: =SUM(F17:F41) -> 0
B44: Selezionare la Classe da elenco a discesa in colonna B della tabella analitica: il riepilogo per classe in alto si aggiorna da solo (SUMIF). Il presente foglio alimenta il foglio 'scenario_riparto'.

Sheet scenario_riparto
B2: SCENARI DI RISANAMENTO · TEST DEL MIGLIOR SODDISFACIMENTO DEI CREDITORI
B3: Confronto tra alternative e cascata di riparto per classe di privilegio
B6: CONFRONTO SCENARI (best interest of creditors test)
B7: Scenario | C7: Attivo realizzabile stimato | D7: Costi di procedura stimati | E7: Attivo netto disponibile | F7: % sodd. Privilegiati | G7: % sodd. Chirografari
B8: Liquidazione giudiziale (baseline) | C8: 0 | D8: 0 | E8: =C8-D8 -> 0 | F8: =IFERROR(MIN(E8,(passivo_creditori!C8+passivo_creditori!C9+passivo_creditori!C10+passivo_creditori!C11))/(passivo_creditori!C8+passivo_creditori!C9+passivo_creditori!C10+passivo_creditori!C11),"n.d.") -> n.d. | G8: =IFERROR(MAX(E8-(passivo_creditori!C8+passivo_creditori!C9+passivo_creditori!C10+passivo_creditori!C11),0)/(passivo_creditori!C12),"n.d.") -> n.d.
B9: Concordato preventivo liquidatorio | C9: 0 | D9: 0 | E9: =C9-D9 -> 0 | F9: =IFERROR(MIN(E9,(passivo_creditori!C8+passivo_creditori!C9+passivo_creditori!C10+passivo_creditori!C11))/(passivo_creditori!C8+passivo_creditori!C9+passivo_creditori!C10+passivo_creditori!C11),"n.d.") -> n.d. | G9: =IFERROR(MAX(E9-(passivo_creditori!C8+passivo_creditori!C9+passivo_creditori!C10+passivo_creditori!C11),0)/(passivo_creditori!C12),"n.d.") -> n.d.
B10: Concordato preventivo in continuita' | C10: 0 | D10: 0 | E10: =C10-D10 -> 0 | F10: =IFERROR(MIN(E10,(passivo_creditori!C8+passivo_creditori!C9+passivo_creditori!C10+passivo_creditori!C11))/(passivo_creditori!C8+passivo_creditori!C9+passivo_creditori!C10+passivo_creditori!C11),"n.d.") -> n.d. | G10: =IFERROR(MAX(E10-(passivo_creditori!C8+passivo_creditori!C9+passivo_creditori!C10+passivo_creditori!C11),0)/(passivo_creditori!C12),"n.d.") -> n.d.
B11: Piano attestato / Accordo di ristrutturazione | C11: 0 | D11: 0 | E11: =C11-D11 -> 0 | F11: =IFERROR(MIN(E11,(passivo_creditori!C8+passivo_creditori!C9+passivo_creditori!C10+passivo_creditori!C11))/(passivo_creditori!C8+passivo_creditori!C9+passivo_creditori!C10+passivo_creditori!C11),"n.d.") -> n.d. | G11: =IFERROR(MAX(E11-(passivo_creditori!C8+passivo_creditori!C9+passivo_creditori!C10+passivo_creditori!C11),0)/(passivo_creditori!C12),"n.d.") -> n.d.
B13: % di soddisfazione stimate in forma sintetica: i Privilegiati (prededucibili + privilegio speciale + privilegio generale) sono soddisfatti in ordine di grado fino a capienza dell'attivo netto; i Chirografari ricevono l'eventuale residuo. E' una stima aggregata di primo orientamento: per il singolo creditore garantito da un bene specifico, il grado di soddisfazione reale dipende dal valore di realizzo di quel bene (cascata dettagliata sotto).
B15: CASCATA DI RIPARTO DETTAGLIATA PER CLASSE (scenario selezionato)
B16: Scenario da dettagliare | C16: Liquidazione giudiziale (baseline)
B17: Attivo netto disponibile (dal confronto sopra) | C17: =INDEX(E8:E11,MATCH(C16,B8:B11,0)) -> 0
B19: Classe | C19: Credito totale | D19: Residuo attivo ante classe | E19: Assegnato | F19: % soddisfazione
B20: Prededucibile | C20: =passivo_creditori!C8 -> 0 | D20: =C17 -> 0 | E20: =MIN(C20,D20) -> 0 | F20: =IFERROR(E20/C20,"n.d.") -> n.d.
B21: Privilegio speciale (ipoteca / pegno) | C21: =passivo_creditori!C9 -> 0 | D21: =MAX(D20-E20,0) -> 0 | E21: =MIN(C21,D21) -> 0 | F21: =IFERROR(E21/C21,"n.d.") -> n.d.
B22: Privilegio generale - lavoratori (art. 2751-bis c.c.) | C22: =passivo_creditori!C10 -> 0 | D22: =MAX(D21-E21,0) -> 0 | E22: =MIN(C22,D22) -> 0 | F22: =IFERROR(E22/C22,"n.d.") -> n.d.
B23: Privilegio generale - tributi e contributi | C23: =passivo_creditori!C11 -> 0 | D23: =MAX(D22-E22,0) -> 0 | E23: =MIN(C23,D23) -> 0 | F23: =IFERROR(E23/C23,"n.d.") -> n.d.
B24: Chirografario | C24: =passivo_creditori!C12 -> 0 | D24: =MAX(D23-E23,0) -> 0 | E24: =MIN(C24,D24) -> 0 | F24: =IFERROR(E24/C24,"n.d.") -> n.d.
B25: TOTALE | C25: =SUM(C20:C24) -> 0 | E25: =SUM(E20:E24) -> 0
B26: Attivo residuo non distribuito | C26: =MAX(D24-E24,0) -> 0
B28: Colonna 'Residuo attivo ante classe' = attivo ancora disponibile prima di soddisfare questa classe. Ogni classe e' soddisfatta fino a concorrenza del credito totale, in ordine di grado; l'eventuale eccedenza passa alla classe successiva (metodo a cascata semplificato per classi omogenee, non sostituisce il piano di riparto analitico per singolo creditore che richiede la ripartizione pro-quota all'interno di ciascuna classe se il credito di classe non e' soddisfatto per intero).

Sheet documenti
B2: CHECKLIST DOCUMENTALE
B3: Raccolta e fascicolazione allegati — stato di avanzamento
B5: Documento | C5: Stato | D5: Data ricezione | E5: Note
B6: SOCIETARI E CAMERALI
B7: Visura camerale aggiornata | C7: Da richiedere
B8: Statuto e atto costitutivo vigenti | C8: Da richiedere
B9: Libro soci / titolare effettivo | C9: Da richiedere
B10: Verbali assembleari ultimi 3 esercizi | C10: Da richiedere
B11: Visura storica cariche societarie | C11: Da richiedere
B13: BILANCI E CONTABILITA'
B14: Bilanci depositati ultimi 3 esercizi | C14: Da richiedere
B15: Situazione contabile infrannuale aggiornata | C15: Da richiedere
B16: Libro giornale e libro inventari | C16: Da richiedere
B17: Registro cespiti ammortizzabili | C17: Da richiedere
B18: Nota integrativa e relazione sulla gestione | C18: Da richiedere
B20: FISCALE E PREVIDENZIALE
B21: Estratto di ruolo Agenzia Entrate-Riscossione | C21: Da richiedere
B22: Certificato carichi pendenti | C22: Da richiedere
B23: Dichiarazioni IVA e IRAP ultimi 3 esercizi | C23: Da richiedere
B24: DURC | C24: Da richiedere
B25: Posizione debitoria INPS/INAIL | C25: Da richiedere
B27: BANCARIO E FINANZIARIO
B28: Centrale rischi Banca d'Italia | C28: Da richiedere
B29: Elenco conti correnti attivi/chiusi | C29: Da richiedere
B30: Piani di ammortamento mutui e finanziamenti | C30: Da richiedere
B31: Contratti di leasing in essere | C31: Da richiedere
B32: Fideiussioni rilasciate/ricevute | C32: Da richiedere
B34: CONTRATTI E GARANZIE
B35: Elenco contratti attivi rilevanti | C35: Da richiedere
B36: Contratti di locazione immobili/rami d'azienda | C36: Da richiedere
B37: Garanzie reali (ipoteche, pegni) iscritte | C37: Da richiedere
B38: Contenziosi e azioni esecutive in corso | C38: Da richiedere
B40: PROCEDURA
B41: Relazione sulle cause della crisi | C41: Da richiedere
B42: Piano industriale / piano di risanamento | C42: Da richiedere
B43: Elenco creditori con importi e cause | C43: Da richiedere
B44: Mandato al professionista incaricato | C44: Da richiedere
B45: Attestazione (se richiesta dalla procedura prescelta) | C45: Da richiedere
B47: Aggiornare lo stato mano a mano che i documenti vengono raccolti: il conteggio in dashboard si aggiorna automaticamente.
